muddy/__init__.py
muddy/constants.py
muddy/exceptions.py
muddy/maker.py
muddy/models.py
muddy/utils.py
muddy/scripts/__init__.py
muddy/scripts/mudcli.py
muddy-2019.7.25.post2.dist-info/LICENSE
muddy-2019.7.25.post2.dist-info/METADATA
muddy-2019.7.25.post2.dist-info/WHEEL
muddy-2019.7.25.post2.dist-info/entry_points.txt
muddy-2019.7.25.post2.dist-info/top_level.txt
muddy-2019.7.25.post2.dist-info/RECORD
