Metadata-Version: 2.1
Name: muddy
Version: 2019.7.25.post2
Summary: UNKNOWN
Home-page: https://github.com/lstn/muddy
Author: Lucas Estienne, Daniel Innes
Author-email: lucas@estienne.sh, daniel.w.innes@gmail.com
License: UNKNOWN
Platform: UNKNOWN
Classifier: Programming Language :: Python :: 3
Classifier: License :: OSI Approved :: MIT License
Classifier: Operating System :: OS Independent
Requires-Dist: Click (<8,>=7)
Requires-Dist: overload (>=1.1)
